[{"Year":2000,"Value":"NaN"},{"Year":2001,"Value":"NaN"},{"Year":2002,"Value":"NaN"},{"Year":2003,"Value":"NaN"},{"Year":2004,"Value":"NaN"},{"Year":2005,"Value":"NaN"},{"Year":2006,"Value":"NaN"},{"Year":2007,"Value":"NaN"},{"Year":2008,"Value":"NaN"},{"Year":2009,"Value":"NaN"},{"Year":2010,"Value":"NaN"},{"Year":2011,"Value":"NaN"},{"Year":2012,"Value":"NaN"},{"Year":2013,"Value":"NaN"},{"Year":2014,"Value":"NaN"},{"Year":2015,"Value":"NaN"},{"Year":2016,"Value":"NaN"},{"Year":2017,"Value":"NaN"},{"Year":2018,"Value":"NaN"},{"Year":2019,"Value":"NaN"},{"Year":2020,"Value":"NaN"},{"Year":2021,"Value":"NaN"},{"Year":2022,"Value":"NaN"},{"Year":2023,"Value":"NaN"}]